<?xml version="1.0" encoding="UTF-8"?>
<objects serializationModel="Studio.02.02.00">
	<object class="EncodingSetting" id="{87b27cde-3b20-4fa5-8c14-6b925adb7fd6}">
		<property name="encodingFormat">
			<value>3</value>
		</property>
		<property name="quality">
			<value>37</value>
		</property>
		<relationship name="platform">
			<destination>{468997fc-fc2d-42c3-8c05-f7f8b3d3ac65}</destination>
		</relationship>
		<relationship name="encodable">
			<destination>{c294463a-1a78-47d8-a300-56ddc8484acd}</destination>
		</relationship>
	</object>
</objects>
