<?xml version="1.0" encoding="UTF-8"?>
<objects serializationModel="Studio.02.02.00">
	<object class="AudioFile" id="{e9e2027b-0768-4852-99b7-b3360d5052a6}">
		<property name="assetPath">
			<value>Assets_Testing/crys_/Space_Crystals/crys_enem/21_03/crys_enem_space_var3-003.wav</value>
		</property>
		<property name="frequencyInKHz">
			<value>44.0999985</value>
		</property>
		<property name="channelCount">
			<value>1</value>
		</property>
		<property name="length">
			<value>4.2318140589569158</value>
		</property>
		<relationship name="masterAssetFolder">
			<destination>{921f1962-17ee-4315-8fb9-ef6616586a6e}</destination>
		</relationship>
	</object>
</objects>
